{
  "$defs": {
    "JobType": {
      "enum": [
        "InitializeNova",
        "IngestNewNova",
        "RefreshPapers",
        "DiscoverSpectraProducts",
        "DownloadAndValidateSpectra",
        "IngestPhotometryDataset",
        "NameCheckAndReconcile"
      ],
      "title": "JobType",
      "type": "string"
    }
  },
  "$id": "nova-cat://schemas/events/name_check_and_reconcile/1.0.0",
  "additionalProperties": false,
  "properties": {
    "attributes": {
      "additionalProperties": true,
      "title": "Attributes",
      "type": "object"
    },
    "correlation_id": {
      "format": "uuid",
      "title": "Correlation Id",
      "type": "string"
    },
    "event_version": {
      "default": "1.0.0",
      "description": "Semantic version for this event contract.",
      "title": "Event Version",
      "type": "string"
    },
    "idempotency_key": {
      "maxLength": 256,
      "minLength": 8,
      "title": "Idempotency Key",
      "type": "string"
    },
    "initiated_at": {
      "format": "date-time",
      "title": "Initiated At",
      "type": "string"
    },
    "job_type": {
      "$ref": "#/$defs/JobType",
      "default": "NameCheckAndReconcile"
    },
    "nova_id": {
      "format": "uuid",
      "title": "Nova Id",
      "type": "string"
    },
    "proposed_aliases": {
      "items": {
        "type": "string"
      },
      "title": "Proposed Aliases",
      "type": "array"
    },
    "proposed_public_name": {
      "anyOf": [
        {
          "type": "string"
        },
        {
          "type": "null"
        }
      ],
      "default": null,
      "title": "Proposed Public Name"
    }
  },
  "required": [
    "idempotency_key",
    "nova_id"
  ],
  "title": "NameCheckAndReconcileEvent",
  "type": "object"
}
